PJYoloVision/__init__.py
PJYoloVision/nn/__init__.py
PJYoloVision/nn/autobackend.py
PJYoloVision/nn/autoshape.py
PJYoloVision/nn/modules.py
PJYoloVision/nn/tasks.py
PJYoloVision/tracker/__init__.py
PJYoloVision/tracker/track.py
PJYoloVision/tracker/trackers/__init__.py
PJYoloVision/tracker/trackers/basetrack.py
PJYoloVision/tracker/trackers/bot_sort.py
PJYoloVision/tracker/trackers/byte_tracker.py
PJYoloVision/tracker/utils/__init__.py
PJYoloVision/tracker/utils/gmc.py
PJYoloVision/tracker/utils/kalman_filter.py
PJYoloVision/tracker/utils/matching.py
PJYoloVision/yolo/__init__.py
PJYoloVision/yolo/cfg/__init__.py
PJYoloVision/yolo/core/__init__.py
PJYoloVision/yolo/core/exporter.py
PJYoloVision/yolo/core/model.py
PJYoloVision/yolo/core/predictor.py
PJYoloVision/yolo/core/results.py
PJYoloVision/yolo/core/trainer.py
PJYoloVision/yolo/core/validator.py
PJYoloVision/yolo/data/__init__.py
PJYoloVision/yolo/data/augment.py
PJYoloVision/yolo/data/base.py
PJYoloVision/yolo/data/build.py
PJYoloVision/yolo/data/dataset.py
PJYoloVision/yolo/data/dataset_wrappers.py
PJYoloVision/yolo/data/utils.py
PJYoloVision/yolo/data/dataloaders/__init__.py
PJYoloVision/yolo/data/dataloaders/stream_loaders.py
PJYoloVision/yolo/data/dataloaders/v5augmentations.py
PJYoloVision/yolo/data/dataloaders/v5loader.py
PJYoloVision/yolo/data/scripts/__init__.py
PJYoloVision/yolo/utils/__init__.py
PJYoloVision/yolo/utils/autobatch.py
PJYoloVision/yolo/utils/benchmarks.py
PJYoloVision/yolo/utils/checks.py
PJYoloVision/yolo/utils/dist.py
PJYoloVision/yolo/utils/downloads.py
PJYoloVision/yolo/utils/files.py
PJYoloVision/yolo/utils/instance.py
PJYoloVision/yolo/utils/loss.py
PJYoloVision/yolo/utils/metrics.py
PJYoloVision/yolo/utils/ops.py
PJYoloVision/yolo/utils/plotting.py
PJYoloVision/yolo/utils/tal.py
PJYoloVision/yolo/utils/torch_utils.py
PJYoloVision/yolo/utils/callbacks/__init__.py
PJYoloVision/yolo/utils/callbacks/base.py
PJYoloVision/yolo/utils/callbacks/clearml.py
PJYoloVision-0.0.6.dist-info/LICENCE.md
PJYoloVision-0.0.6.dist-info/METADATA
PJYoloVision-0.0.6.dist-info/WHEEL
PJYoloVision-0.0.6.dist-info/top_level.txt
PJYoloVision-0.0.6.dist-info/RECORD
