Metadata-Version: 2.1
Name: PJYoloVision
Version: 0.0.6
Summary: The object detection models in PJYoloVision can detect and locate objects in real-time images and video streams. 
Home-page: https://github.com/erfanzar/PJYoloVision
Author: Erfan Zare Chavoshi
Author-email: erfanzare82@eyahoo.com
License: UNKNOWN
Keywords: machine learning,deep learning,pytorch
Platform: UNKNOWN
Classifier: Development Status :: 3 - Alpha
Classifier: Intended Audience :: Developers
Classifier: Topic :: Scientific/Engineering :: Artificial Intelligence
Classifier: License :: OSI Approved :: Apache Software License
Classifier: Programming Language :: Python :: 3
Classifier: Programming Language :: Python :: 3.8
Classifier: Programming Language :: Python :: 3.9
Classifier: Programming Language :: Python :: 3.10
Classifier: Programming Language :: Python :: 3.11
Requires-Python: >=3.8
License-File: LICENCE.md
Requires-Dist: torch (>=1.13.0)
